Metadata-Version: 2.1
Name: odoo-addon-currency-rate-update-nbp
Version: 16.0.1.0.0.2
Summary: Allows to download currency exchange rates from National bank of Poland
Home-page: https://github.com/OCA/l10n-poland
Author: Akretion, Odoo Community Association (OCA)
Author-email: support@odoo-community.org
License: AGPL-3
Platform: UNKNOWN
Classifier: Programming Language :: Python
Classifier: Framework :: Odoo
Classifier: Framework :: Odoo :: 16.0
Classifier: License :: OSI Approved :: GNU Affero General Public License v3
Requires-Python: >=3.10
Requires-Dist: odoo-addon-currency-rate-update <16.1dev,>=16.0dev
Requires-Dist: odoo <16.1dev,>=16.0a
